LICENSE.TXT
README.md
setup.py
erd_from_json_table_schema.egg-info/PKG-INFO
erd_from_json_table_schema.egg-info/SOURCES.txt
erd_from_json_table_schema.egg-info/dependency_links.txt
erd_from_json_table_schema.egg-info/requires.txt
erd_from_json_table_schema.egg-info/top_level.txt
jts_erd/__init__.py
jts_erd/jts_erd.py